pymyenergi/VERSION
pymyenergi/__init__.py
pymyenergi/base_device.py
pymyenergi/cli.py
pymyenergi/client.py
pymyenergi/connection.py
pymyenergi/ct.py
pymyenergi/eddi.py
pymyenergi/exceptions.py
pymyenergi/harvi.py
pymyenergi/libbi.py
pymyenergi/zappi.py
pymyenergi-0.2.3.dist-info/licenses/LICENSE
pymyenergi-0.2.3.dist-info/METADATA
pymyenergi-0.2.3.dist-info/WHEEL
pymyenergi-0.2.3.dist-info/entry_points.txt
pymyenergi-0.2.3.dist-info/top_level.txt
pymyenergi-0.2.3.dist-info/RECORD
