Metadata-Version: 2.4
Name: pymyenergi
Version: 0.2.3
Summary: Python library and CLI for communicating with myenergi API.
Home-page: https://github.com/cjne/pymyenergi
Author: Johan Isaksson
Author-email: johan@generatorhallen.se
License: MIT
Classifier: License :: OSI Approved :: MIT License
Classifier: Programming Language :: Python
Classifier: Operating System :: OS Independent
Requires-Python: >=3.6
License-File: LICENSE
Requires-Dist: httpx
Requires-Dist: pycognito
Dynamic: author
Dynamic: author-email
Dynamic: classifier
Dynamic: description
Dynamic: description-content-type
Dynamic: home-page
Dynamic: license
Dynamic: license-file
Dynamic: requires-dist
Dynamic: requires-python
Dynamic: summary
